MANIFEST.in
README.md
requirements.txt
setup.cfg
setup.py
NumParse.egg-info/PKG-INFO
NumParse.egg-info/SOURCES.txt
NumParse.egg-info/dependency_links.txt
NumParse.egg-info/requires.txt
NumParse.egg-info/top_level.txt
num_parse/NumParser.py
num_parse/RangeValue.py
num_parse/__init__.py
num_parse/word_to_num_values.py
num_parse/tests/__init__.py
num_parse/tests/test_num_parsing.py
num_parse/tests/test_range_value.py
num_parse/unit_definitions/.basic_units.txt.swp
num_parse/unit_definitions/__init__.py
num_parse/unit_definitions/basic_units.txt
num_parse/unit_definitions/constants_en.txt