Metadata-Version: 2.1
Name: NumParse
Version: 0.1.1
Summary: A package for extracting numeric values/ranges from strings.
Home-page: https://github.com/nu-c3lab/c3-NumParse
Author: C3 Lab
Author-email: markosterbentz2023@u.northwestern.edu
License: UNKNOWN
Platform: UNKNOWN
Requires-Python: >=3.7
